topsis/__main__.py
Topsis_Sanyam_101903481-1.0.1.dist-info/LICENSE
Topsis_Sanyam_101903481-1.0.1.dist-info/METADATA
Topsis_Sanyam_101903481-1.0.1.dist-info/WHEEL
Topsis_Sanyam_101903481-1.0.1.dist-info/entry_points.txt
Topsis_Sanyam_101903481-1.0.1.dist-info/top_level.txt
Topsis_Sanyam_101903481-1.0.1.dist-info/RECORD
