Metadata-Version: 2.1
Name: Topsis-Sanyam-101903481
Version: 1.0.1
Summary: Package to calculate the TOPSIS Score and Rank
Author: Sanyam Sharma
Author-email: ssharma6_be19@thapar.edu
License: MIT
Platform: UNKNOWN
Classifier: License :: OSI Approved :: MIT License
Classifier: Programming Language :: Python :: 3.6
Classifier: Programming Language :: Python :: 3.7
Classifier: Programming Language :: Python :: 3.8
License-File: LICENSE
Requires-Dist: pandas
